{
  "animateLoading": true,
  "backgroundColor": "#FFFFFF",
  "borderColor": "#E0DEDE",
  "borderRadius": "{{appsmith.theme.borderRadius.appBorderRadius}}",
  "borderWidth": "1",
  "bottomRow": 48,
  "boxShadow": "{{appsmith.theme.boxShadow.appBoxShadow}}",
  "children": [
    {
      "borderRadius": "{{appsmith.theme.borderRadius.appBorderRadius}}",
      "bottomRow": 480,
      "boxShadow": "{{appsmith.theme.boxShadow.appBoxShadow}}",
      "canExtend": false,
      "containerStyle": "none",
      "detachFromLayout": true,
      "dynamicBindingPathList": [
        {
          "key": "borderRadius"
        },
        {
          "key": "boxShadow"
        }
      ],
      "dynamicHeight": "AUTO_HEIGHT",
      "flexLayers": [],
      "isLoading": false,
      "isVisible": true,
      "key": "o0ks9jmswh",
      "leftColumn": 0,
      "maxDynamicHeight": 9000,
      "minDynamicHeight": 4,
      "minHeight": 100,
      "minWidth": 450,
      "mobileBottomRow": 100,
      "mobileLeftColumn": 0,
      "mobileRightColumn": 486,
      "mobileTopRow": 0,
      "needsErrorInfo": false,
      "parentColumnSpace": 1,
      "parentId": "oaqvnfwwei",
      "parentRowSpace": 1,
      "renderMode": "CANVAS",
      "responsiveBehavior": "fill",
      "rightColumn": 486,
      "topRow": 0,
      "type": "CANVAS_WIDGET",
      "version": 1,
      "widgetId": "39iwfd2527",
      "widgetName": "Canvas20"
    }
  ],
  "containerStyle": "card",
  "dynamicBindingPathList": [
    {
      "key": "borderRadius"
    },
    {
      "key": "boxShadow"
    }
  ],
  "dynamicHeight": "AUTO_HEIGHT",
  "flexVerticalAlignment": "stretch",
  "isCanvas": true,
  "isLoading": false,
  "isVisible": true,
  "key": "gtu9xbvqqz",
  "leftColumn": 20,
  "maxDynamicHeight": 9000,
  "minDynamicHeight": 10,
  "minWidth": 450,
  "mobileBottomRow": 124,
  "mobileLeftColumn": 7,
  "mobileRightColumn": 31,
  "mobileTopRow": 114,
  "needsErrorInfo": false,
  "originalBottomRow": 48,
  "originalTopRow": 0,
  "parentColumnSpace": 20.25,
  "parentId": "0",
  "parentRowSpace": 10,
  "renderMode": "CANVAS",
  "responsiveBehavior": "fill",
  "rightColumn": 42,
  "shouldScrollContents": true,
  "topRow": 0,
  "type": "CONTAINER_WIDGET",
  "version": 1,
  "widgetId": "oaqvnfwwei",
  "widgetName": "SiteTableContainer"
}